hue_sunrise/__init__.py
hue_sunrise/colors.py
hue_sunrise/connector.py
hue_sunrise/main.py
hue_sunrise/scene.py
hue_sunrise/state.py
hue_sunrise-0.6.59.dist-info/entry_points.txt
hue_sunrise-0.6.59.dist-info/WHEEL
hue_sunrise-0.6.59.dist-info/METADATA
hue_sunrise-0.6.59.dist-info/RECORD
